newsme/__init__.py
newsme/html_creator.py
newsme/mail.py
newsme/news.py
newsme-0.0.3.dist-info/LICENSE
newsme-0.0.3.dist-info/METADATA
newsme-0.0.3.dist-info/WHEEL
newsme-0.0.3.dist-info/top_level.txt
newsme-0.0.3.dist-info/RECORD
