Metadata-Version: 2.1
Name: newsme
Version: 0.0.3
Summary: package for simple interaction with NewsApi and sending html mails
Home-page: https://github.com/lunfman/NewsMe
Author: lunfman
Author-email: 
License: MIT License
Project-URL: Bug Tracker, https://github.com/lunfman/NewsMe/issues
Platform: UNKNOWN
Requires-Python: >=3.6
License-File: LICENSE
Requires-Dist: requests (==2.25.1)
